pstr/__init__.py
pstr/_modidx.py
pstr/chck.py
pstr/filt.py
pstr/fuzz.py
pstr/join.py
pstr/path.py
pstr/pttn.py
pstr/repl.py
pstr/sens.py
pstr/snek.py
pstr/util.py
pstr/cons/__init__.py
pstr/enum/__init__.py
pstr/enum/cell.py
pstr/enum/path.py
pstr/enum/tree.py
pstr/enum/unit.py
pstr/fmts/__init__.py
pstr/fmts/byte.py
pstr/fmts/numb.py
pstr/fmts/path.py
pstr/fmts/unit.py
pstr/nchr/__init__.py
pstr/nchr/core.py
pstr/nlit/__init__.py
pstr/nlit/args.py
pstr/nlit/byte.py
pstr/nlit/cell.py
pstr/nlit/docs.py
pstr/nlit/dund.py
pstr/nlit/expr.py
pstr/nlit/exts.py
pstr/nlit/mods.py
pstr/nlit/path.py
pstr/nlit/plot.py
pstr/nlit/sund.py
pstr/nlit/tens.py
pstr/nlit/tree.py
pstr/nlit/unit.py
pstr/nlit/vstr.py
pstr/util/__init__.py
pstr/util/core.py
pstr/util/exts.py
pstr/util/path.py
pstr-0.0.49.dist-info/LICENSE
pstr-0.0.49.dist-info/METADATA
pstr-0.0.49.dist-info/WHEEL
pstr-0.0.49.dist-info/entry_points.txt
pstr-0.0.49.dist-info/top_level.txt
pstr-0.0.49.dist-info/RECORD
