Metadata-Version: 2.1
Name: pstr
Version: 0.0.49
Summary: pstr
Home-page: https://github.com/dsm-72/pstr
Author: dsm-72
Author-email: sumner.magruder@yale.edu
License: Apache Software License 2.0
Keywords: power string pstr prepstr strpre str string prep sensitivity insensitive re snake case strprep fuzstr nymstr nym snek
Classifier: Development Status :: 4 - Beta
Classifier: Intended Audience :: Developers
Classifier: Natural Language :: English
Classifier: Programming Language :: Python :: 3.11
Classifier: License :: OSI Approved :: Apache Software License
Requires-Python: >=3.11
License-File: LICENSE
Requires-Dist: atyp
Requires-Dist: ltyp
Requires-Dist: chck
Requires-Dist: nchr
Requires-Dist: nlit
Requires-Dist: pfmt
Requires-Dist: pttn
Requires-Dist: regsyn
Requires-Dist: idfunc
Requires-Dist: ispec
Requires-Dist: urllib3
Requires-Dist: atup
Provides-Extra: dev
